{
  "org.boothub.java-groovy": {
    "name": "Java / Groovy",
    "caption": "A feature-rich Gradle-based skeleton for Java and/or Groovy projects.",
    "usageCount": 0,
    "ratingCount": 0,
    "ratingSum": 0,
    "sortingWeight": 1,
    "entries": {
      "1.0.0": {
        "usageCount": 0,
        "ratingCount": 0,
        "ratingSum": 0,
        "sortingWeight": 1,
        "url": "https://github.com/boothub-org/boothub-template-java-groovy/releases/download/v1.0.0/java-groovy-1.0.0.zip",
        "size": 81319,
        "sha": "1c6b6d541f5b005c1f2990c830f61c9e04bffd3fa4323fbf352853df4e3864ba",
        "id": "org.boothub.java-groovy",
        "version": "1.0.0",
        "name": "Java / Groovy",
        "caption": "A feature-rich Gradle-based skeleton for Java and/or Groovy projects.",
        "minimumRequiredBootHub": "0.0.0",
        "authors": [],
        "tags": []
      }
    }
  },
  "org.boothub.meta-template": {
    "name": "Meta-Template",
    "caption": "A template for creating BootHub templates.",
    "usageCount": 0,
    "ratingCount": 0,
    "ratingSum": 0,
    "sortingWeight": 1,
    "entries": {
      "1.0.0": {
        "usageCount": 0,
        "ratingCount": 0,
        "ratingSum": 0,
        "sortingWeight": 1,
        "url": "https://github.com/boothub-org/boothub-meta-template/releases/download/v1.0.0/meta-template-1.0.0.zip",
        "size": 124826,
        "sha": "754fc10a70237f2997ddb7a2c7dd3be0e702d9cb39826bbe63ae5a99c4b7a69c",
        "id": "org.boothub.meta-template",
        "version": "1.0.0",
        "name": "Meta-Template",
        "caption": "A template for creating BootHub templates.",
        "minimumRequiredBootHub": "0.0.0",
        "authors": [],
        "tags": []
      }
    }
  }
}